flask_mailgun.py
setup.py
Flask_Mailgun.egg-info/PKG-INFO
Flask_Mailgun.egg-info/SOURCES.txt
Flask_Mailgun.egg-info/dependency_links.txt
Flask_Mailgun.egg-info/not-zip-safe
Flask_Mailgun.egg-info/requires.txt
Flask_Mailgun.egg-info/top_level.txt