Metadata-Version: 1.0
Name: Flask-Mailgun
Version: 0.2
Summary: Adds Mailgun support to Flask applications
Home-page: http://github.com/sleekslush/flask-mailgun
Author: Craig Slusher
Author-email: cslush@gmail.com
License: BSD
Platform: any
Classifier: Development Status :: 4 - Beta
Classifier: Environment :: Web Environment
Classifier: Intended Audience :: Developers
Classifier: License :: OSI Approved :: BSD License
Classifier: Operating System :: OS Independent
Classifier: Programming Language :: Python
Classifier: Topic :: Internet :: WWW/HTTP :: Dynamic Content
Classifier: Topic :: Software Development :: Libraries :: Python Modules
